jax_md/__init__.py
jax_md/dataclasses.py
jax_md/elasticity.py
jax_md/energy.py
jax_md/interpolate.py
jax_md/io.py
jax_md/minimize.py
jax_md/nn.py
jax_md/partition.py
jax_md/quantity.py
jax_md/rigid_body.py
jax_md/simulate.py
jax_md/smap.py
jax_md/space.py
jax_md/test_util.py
jax_md/tpu.py
jax_md/units.py
jax_md/util.py
jax_md/_energy/__init__.py
jax_md/_energy/electrostatics.py
jax_md/_nn/__init__.py
jax_md/_nn/behler_parrinello.py
jax_md/_nn/e3nn_layer.py
jax_md/_nn/gnome.py
jax_md/_nn/nequip.py
jax_md/_nn/util.py
jax_md/a2c/__init__.py
jax_md/a2c/a2c_workflow.py
jax_md/a2c/crystallizer_utils.py
jax_md/a2c/make_amorphous_utils.py
jax_md/colab_tools/__init__.py
jax_md/colab_tools/renderer.py
jax_md/colab_tools/visualization.html
jax_md/reaxff/__init__.py
jax_md/reaxff/reaxff_energy.py
jax_md/reaxff/reaxff_forcefield.py
jax_md/reaxff/reaxff_helper.py
jax_md/reaxff/reaxff_interactions.py
jax_md-0.2.27.dist-info/METADATA
jax_md-0.2.27.dist-info/WHEEL
jax_md-0.2.27.dist-info/licenses/LICENSE
jax_md-0.2.27.dist-info/licenses/LICENSE_SHORT
jax_md-0.2.27.dist-info/RECORD
