Metadata-Version: 2.4
Name: jax-md
Version: 0.2.27
Summary: Differentiable, Hardware Accelerated, Molecular Dynamics
Project-URL: Homepage, https://github.com/google/jax-md
Project-URL: Documentation, https://arxiv.org/abs/1912.04232
Project-URL: Repository, https://github.com/google/jax-md
Project-URL: Bug Tracker, https://github.com/google/jax-md/issues
Project-URL: Download, https://pypi.org/project/jax-md/
Author-email: Google <jax-md-dev@google.com>
Maintainer-email: Google <jax-md-dev@google.com>
License-Expression: Apache-2.0
License-File: LICENSE
License-File: LICENSE_SHORT
Keywords: differentiable,jax,molecular-dynamics,physics,simulation
Classifier: Intended Audience :: Developers
Classifier: Intended Audience :: Science/Research
Classifier: Operating System :: MacOS
Classifier: Operating System :: POSIX :: Linux
Classifier: Programming Language :: Python :: 3.11
Classifier: Programming Language :: Python :: 3.12
Classifier: Programming Language :: Python :: 3.13
Classifier: Topic :: Scientific/Engineering
Classifier: Topic :: Software Development
Requires-Python: >=3.11
Requires-Dist: absl-py
Requires-Dist: dm-haiku
Requires-Dist: e3nn-jax
Requires-Dist: einops
Requires-Dist: flax
Requires-Dist: frozendict
Requires-Dist: jax>=0.5.0
Requires-Dist: jaxlib>=0.5.0
Requires-Dist: jraph
Requires-Dist: ml-collections
Requires-Dist: numpy
Requires-Dist: optax
Requires-Dist: pymatgen
